{
  "run_date": "2026-03-16T06:55:11.628272",
  "analysis_date": "2026-03-16T06:41:25.928823",
  "total_stocks": 771,
  "russell_1000_stocks": 1018,
  "successful_fetches": 771,
  "processing_time_seconds": 825.699452,
  "data_sources": {
    "sec_edgar_coverage": "771/771 (100.0%)",
    "yahoo_finance_coverage": "771/771 (100.0%)",
    "hybrid_approach": true,
    "point_in_time_accuracy": true
  },
  "enhancements": {
    "look_ahead_bias_eliminated": true,
    "sec_point_in_time_fundamentals": true,
    "enhanced_quality_metrics": true,
    "value_trap_avoidance": true
  },
  "version": "2.1-hybrid-pit",
  "environment": {
    "offline_mode": false
  }
}