{
  "run_date": "2026-03-09T06:45:00.900369",
  "analysis_date": "2026-03-09T06:30:14.025797",
  "total_stocks": 776,
  "russell_1000_stocks": 1018,
  "successful_fetches": 776,
  "processing_time_seconds": 886.874575,
  "data_sources": {
    "sec_edgar_coverage": "776/776 (100.0%)",
    "yahoo_finance_coverage": "776/776 (100.0%)",
    "hybrid_approach": true,
    "point_in_time_accuracy": true
  },
  "enhancements": {
    "look_ahead_bias_eliminated": true,
    "sec_point_in_time_fundamentals": true,
    "enhanced_quality_metrics": true,
    "value_trap_avoidance": true
  },
  "version": "2.1-hybrid-pit",
  "environment": {
    "offline_mode": false
  }
}